gwenflow/__init__.py
gwenflow/exceptions.py
gwenflow/logger.py
gwenflow/version.py
gwenflow/agents/__init__.py
gwenflow/agents/agent.py
gwenflow/agents/chat.py
gwenflow/agents/prompts.py
gwenflow/agents/react_agent.py
gwenflow/api/__init__.py
gwenflow/api/api.py
gwenflow/embeddings/__init__.py
gwenflow/embeddings/base.py
gwenflow/embeddings/gwenlake.py
gwenflow/flows/__init__.py
gwenflow/flows/autoflow.py
gwenflow/flows/base.py
gwenflow/flows/drawflow.py
gwenflow/llms/__init__.py
gwenflow/llms/base.py
gwenflow/llms/azure/__init__.py
gwenflow/llms/azure/chat.py
gwenflow/llms/deepseek/__init__.py
gwenflow/llms/deepseek/chat.py
gwenflow/llms/google/__init__.py
gwenflow/llms/google/chat.py
gwenflow/llms/gwenlake/__init__.py
gwenflow/llms/gwenlake/chat.py
gwenflow/llms/mistral/__init__.py
gwenflow/llms/mistral/chat.py
gwenflow/llms/ollama/__init__.py
gwenflow/llms/ollama/chat.py
gwenflow/llms/openai/__init__.py
gwenflow/llms/openai/chat.py
gwenflow/memory/__init__.py
gwenflow/memory/base.py
gwenflow/memory/chat_memory_buffer.py
gwenflow/parsers/__init__.py
gwenflow/parsers/text_splitters.py
gwenflow/prompts/__init__.py
gwenflow/prompts/pipeline.py
gwenflow/prompts/template.py
gwenflow/readers/__init__.py
gwenflow/readers/base.py
gwenflow/readers/directory.py
gwenflow/readers/docx.py
gwenflow/readers/json.py
gwenflow/readers/pdf.py
gwenflow/readers/text.py
gwenflow/readers/website.py
gwenflow/reranker/__init__.py
gwenflow/reranker/base.py
gwenflow/reranker/gwenlake.py
gwenflow/retriever/__init__.py
gwenflow/retriever/base.py
gwenflow/stores/__init__.py
gwenflow/stores/opensearch.py
gwenflow/telemetry/__init__.py
gwenflow/telemetry/base.py
gwenflow/telemetry/decorator.py
gwenflow/telemetry/azure/__init__.py
gwenflow/telemetry/azure/azure_instrument.py
gwenflow/telemetry/openai/__init__.py
gwenflow/telemetry/openai/openai_instrument.py
gwenflow/tools/__init__.py
gwenflow/tools/base.py
gwenflow/tools/duckduckgo.py
gwenflow/tools/function.py
gwenflow/tools/pdf.py
gwenflow-0.8.3.dist-info/licenses/LICENSE.txt
gwenflow-0.8.3.dist-info/METADATA
gwenflow-0.8.3.dist-info/WHEEL
gwenflow-0.8.3.dist-info/top_level.txt
gwenflow-0.8.3.dist-info/RECORD
