Metadata-Version: 2.4
Name: gwenflow
Version: 0.8.3
Summary: A framework for orchestrating applications powered by autonomous AI agents and LLMs.
Author-email: Gwenlake <info@gwenlake.com>, Sylvain Barthélémy <sylvain.barthelemy@gwenlake.com>, Guillaume Beguec <guillaume.beguec@gwenlake.com>, Antoine de Parthenay <antoine.departhenay@gwenlake.com>
License: MIT License
Project-URL: Homepage, https://gwenlake.com
Project-URL: Source, https://github.com/gwenlake/gwenflow
Keywords: gwenflow,gwenlake,agents,llms,ai,ml,nlp,framework
Classifier: Development Status :: 3 - Alpha
Classifier: Intended Audience :: Science/Research
Classifier: License :: Freely Distributable
Classifier: License :: OSI Approved :: MIT License
Classifier: Operating System :: OS Independent
Classifier: Programming Language :: Python :: 3.11
Classifier: Programming Language :: Python :: 3.12
Classifier: Topic :: Scientific/Engineering :: Artificial Intelligence
Requires-Python: <3.14,>=3.11
License-File: LICENSE.txt
Requires-Dist: httpx
Requires-Dist: pydantic
Requires-Dist: tqdm
Requires-Dist: pyyaml
Requires-Dist: beautifulsoup4
Requires-Dist: fsspec
Requires-Dist: rich
Requires-Dist: tiktoken
Requires-Dist: openai==2.15.0
Requires-Dist: langchain
Requires-Dist: boto3
Requires-Dist: pyarrow
Requires-Dist: lancedb
Requires-Dist: qdrant-client
Requires-Dist: jinja2
Requires-Dist: markupsafe
Requires-Dist: dirtyjson
Requires-Dist: asyncio==3.4.3
Requires-Dist: tenacity==9.0.0
Requires-Dist: mcp==1.6.0
Requires-Dist: faiss-cpu==1.11.0.post1
Requires-Dist: opentelemetry-api==1.29
Requires-Dist: opentelemetry-sdk==1.29
Requires-Dist: opentelemetry-exporter-otlp-proto-http==1.29.0
Requires-Dist: openinference-instrumentation-openai==0.1.41
Dynamic: license-file
